frontrunner_sdk/__init__.py
frontrunner_sdk/ioc.py
frontrunner_sdk/sdk.py
frontrunner_sdk/sync.py
frontrunner_sdk/clients/__init__.py
frontrunner_sdk/clients/denom_factory.py
frontrunner_sdk/clients/injective_chain.py
frontrunner_sdk/clients/injective_faucet.py
frontrunner_sdk/clients/injective_light_client_daemon.py
frontrunner_sdk/clients/injective_order_hasher.py
frontrunner_sdk/clients/openapi_client.py
frontrunner_sdk/clients/gas_estimators/__init__.py
frontrunner_sdk/clients/gas_estimators/gas_estimator.py
frontrunner_sdk/clients/gas_estimators/multiplier_table_gas_estimator.py
frontrunner_sdk/clients/gas_estimators/offsetting_gas_estimator.py
frontrunner_sdk/clients/gas_estimators/simulation_gas_estimator.py
frontrunner_sdk/clients/gas_estimators/table_gas_estimator.py
frontrunner_sdk/commands/__init__.py
frontrunner_sdk/commands/base.py
frontrunner_sdk/commands/frontrunner/__init__.py
frontrunner_sdk/commands/frontrunner/find_markets.py
frontrunner_sdk/commands/frontrunner/get_leagues.py
frontrunner_sdk/commands/frontrunner/get_markets.py
frontrunner_sdk/commands/frontrunner/get_props.py
frontrunner_sdk/commands/frontrunner/get_sport_entities.py
frontrunner_sdk/commands/frontrunner/get_sport_events.py
frontrunner_sdk/commands/frontrunner/get_sports.py
frontrunner_sdk/commands/injective/__init__.py
frontrunner_sdk/commands/injective/cancel_orders.py
frontrunner_sdk/commands/injective/create_orders.py
frontrunner_sdk/commands/injective/create_wallet.py
frontrunner_sdk/commands/injective/fund_external_subaccount.py
frontrunner_sdk/commands/injective/fund_external_wallet.py
frontrunner_sdk/commands/injective/fund_subaccount.py
frontrunner_sdk/commands/injective/fund_wallet_from_faucet.py
frontrunner_sdk/commands/injective/get_account_portfolio.py
frontrunner_sdk/commands/injective/get_order_books.py
frontrunner_sdk/commands/injective/get_orders.py
frontrunner_sdk/commands/injective/get_positions.py
frontrunner_sdk/commands/injective/get_trades.py
frontrunner_sdk-0.8.4.dist-info/METADATA
frontrunner_sdk-0.8.4.dist-info/WHEEL
frontrunner_sdk-0.8.4.dist-info/entry_points.txt
frontrunner_sdk-0.8.4.dist-info/namespace_packages.txt
frontrunner_sdk-0.8.4.dist-info/top_level.txt
frontrunner_sdk-0.8.4.dist-info/RECORD
